{
  "servant": {
    "no": "38",
    "name": "库・丘林",
    "clazz": "caster",
    "rare": 3,
    "cost": 7,
    "tenchizin": "天"
  },
  "card": {
    "arts": {
      "count": 3,
      "hit": 1
    },
    "quick": {
      "count": 1,
      "hit": 2
    },
    "buster": {
      "count": 1,
      "hit": 1
    }
  },
  "status": [
    {
      "level": "Lv70",
      "hp": 9604,
      "atk": 6580
    }
  ],
  "hidden": {
    "na": 1.6,
    "nd": 3,
    "dr": 42,
    "starcollection": 49,
    "staroccurrence": 10.9,
    "tag": [
      "秩序",
      "中庸",
      "男",
      "サーヴァント",
      "人型",
      "神性",
      "愛する者"
    ]
  },
  "classskill": [
    {
      "type": "阵地作成", "name": "阵地作成B",
      "effect": [
        {
          "type": "蓝放",
          "desc": "自身的Arts卡性能上升",
          "magnification": "8%"
        }
      ]
    },
    {
      "type": "神性", "name": "神性B",
      "effect": [
        {
          "type": "付与伤害附加状态",
          "desc": "付与自身伤害附加状态",
          "magnification": "175"
        }
      ]
    }
  ],
  "hogu": {
    "name": "灼烧殆尽的炎笼(Wicker Man)",
    "card": "Buster",
    "effect": [
      {
        "type": "红放",
        "turn":  3,
        "count": 0,
        "target": "自身",
        "beforeafter": "发动前",
        "lvoc": "LV",
        "desc": "自身的Buster Card 性能上升(3T)",
        "v1": "20",
        "v2": "20",
        "v3": "20",
        "v4": "20",
        "v5": "20"
      },
      {
        "type": "攻击",
        "turn": 0,
        "count": 0,
        "target": "敌方全体",
        "beforeafter": "发动前",
        "lvoc": "LV",
        "desc": "对敌方全体发动强力攻击",
        "v1": "400",
        "v2": "500",
        "v3": "550",
        "v4": "575",
        "v5": "600"
      },
      {
        "type": "降防",
        "turn":  3,
        "count": 0,
        "target": "敌方全体",
        "beforeafter": "发动后",
        "lvoc": "OC",
        "desc": "敌方防御力下降(3T)",
        "v1": "10",
        "v2": "15",
        "v3": "20",
        "v4": "25",
        "v5": "30"
      },
      {
        "type": "付与灼烧状态",
        "turn":  0,
        "count": 0,
        "target": "敌方全体",
        "beforeafter": "发动后",
        "lvoc": "OC",
        "desc": "付与灼烧(10T)",
        "v1": "300",
        "v2": "600",
        "v3": "900",
        "v4": "1200",
        "v5": "1500"
      }
    ],
    "type": "全体",
    "hit": 1
  },
  "skill1": {
    "name": "原初のルーン",
    "ct": 7,
    "effects": [
      {
        "type": "暴击威力提升",
        "turn":  3,
        "count": 0,
        "target": "自身",
        "desc": "自身的威力上升(3T)",
        "v1": "20",
        "v2": "23",
        "v3": "26",
        "v4": "29",
        "v5": "32",
        "v6": "35",
        "v7": "38",
        "v8": "41",
        "v9": "44",
        "v10": "50"
      },
      {
        "type": "弱化耐性提升",
        "turn":  3,
        "count": 0,
        "target": "自身",
        "desc": "＆弱体耐性上升(3T)",
        "v1": "20",
        "v2": "23",
        "v3": "26",
        "v4": "29",
        "v5": "32",
        "v6": "35",
        "v7": "38",
        "v8": "41",
        "v9": "44",
        "v10": "50"
      },
      {
        "type": "充能",
        "turn": 0,
        "count": 0,
        "target": "自身",
        "desc": "NP增加",
        "v1": "20",
        "v2": "21",
        "v3": "22",
        "v4": "23",
        "v5": "24",
        "v6": "25",
        "v7": "26",
        "v8": "27",
        "v9": "28",
        "v10": "30"
      }
    ]
  , "avatar": "暴击威力提升"},
  "skill2": {
    "name": "矢避けの加護A",
    "ct": 7,
    "effects": [
      {
        "type": "回避",
        "turn": 0,
        "count": 3,
        "target": "自身",
        "desc": "自身に回避状态を付与(3回)",
        "v1": "",
        "v2": "",
        "v3": "",
        "v4": "",
        "v5": "",
        "v6": "",
        "v7": "",
        "v8": "",
        "v9": "",
        "v10": ""
      },
      {
        "type": "加防",
        "turn":  3,
        "count": 0,
        "target": "自身",
        "desc": "防御力上升 (3T)",
        "v1": "9",
        "v2": "9.9",
        "v3": "10.8",
        "v4": "11.7",
        "v5": "12.6",
        "v6": "13.5",
        "v7": "14.4",
        "v8": "15.3",
        "v9": "16.2",
        "v10": "18"
      }
    ]
  , "avatar": "回避"},
  "skill3": {
    "name": "仕切り直しC",
    "ct": 7,
    "effects": [
      {
        "type": "弱化解除",
        "turn": 0,
        "count": 0,
        "target": "自身",
        "desc": "自身弱化状态解除",
        "v1": "",
        "v2": "",
        "v3": "",
        "v4": "",
        "v5": "",
        "v6": "",
        "v7": "",
        "v8": "",
        "v9": "",
        "v10": ""
      },
      {
        "type": "回血",
        "turn": 0,
        "count": 0,
        "target": "自身",
        "desc": "HP回复",
        "v1": "500",
        "v2": "600",
        "v3": "700",
        "v4": "800",
        "v5": "900",
        "v6": "1000",
        "v7": "1100",
        "v8": "1200",
        "v9": "1300",
        "v10": "1500"
      }
    ], "avatar": "弱化解除"
  }
}
